humanoid/__init__.py
humanoid/credential_management.py
humanoid/captcha_solver/__init__.py
humanoid/captcha_solver/error.py
humanoid/captcha_solver/network.py
humanoid/captcha_solver/solver.py
humanoid/captcha_solver/backend/__init__.py
humanoid/captcha_solver/backend/antigate.py
humanoid/captcha_solver/backend/base.py
humanoid/captcha_solver/backend/browser.py
humanoid/captcha_solver/backend/rucaptcha.py
humanoid/captcha_solver/backend/twocaptcha.py
humanoid/internet_search/__init__.py
humanoid/internet_search/acclaim.py
humanoid/internet_search/google.py
humanoid/tests/__init__.py
humanoid/tests/test_browser.py
humanoid/tests/test_solver.py
humanoid/utilities/__init__.py
Humanoid-0.0.1.dist-info/LICENSE.md
Humanoid-0.0.1.dist-info/METADATA
Humanoid-0.0.1.dist-info/WHEEL
Humanoid-0.0.1.dist-info/top_level.txt
Humanoid-0.0.1.dist-info/RECORD
