Metadata-Version: 2.1
Name: Humanoid
Version: 0.0.1
Summary: An SDK for artificial-human interaction with websites, namely Google search and CAPTCHAs.
Maintainer-email: Michael Spece <Michael@Spece.AI>
License: 
Project-URL: Homepage, https://github.com/ArtificialHumanoid/Humanoid
Classifier: Programming Language :: Python
Classifier: Programming Language :: Python :: 3
Classifier: Programming Language :: Python :: 3.7
Classifier: Programming Language :: Python :: 3.8
Classifier: Programming Language :: Python :: 3.9
Classifier: Programming Language :: Python :: 3.10
Classifier: Programming Language :: Python :: 3.11
Classifier: License :: Other/Proprietary License
Classifier: Development Status :: 4 - Beta
Classifier: Intended Audience :: Developers
Classifier: Operating System :: OS Independent
Classifier: Topic :: Software Development :: Libraries :: Python Modules
Classifier: Topic :: Internet :: WWW/HTTP
Classifier: Typing :: Typed
Requires-Python: >=3.7
License-File: LICENSE.md
